pynavt/__init__.py
pynavt/base.py
pynavt-1.0.8.dist-info/LICENSE
pynavt-1.0.8.dist-info/METADATA
pynavt-1.0.8.dist-info/WHEEL
pynavt-1.0.8.dist-info/entry_points.txt
pynavt-1.0.8.dist-info/top_level.txt
pynavt-1.0.8.dist-info/RECORD
